embeddingcache/__init__.py
embeddingcache/computeembeddings.py
embeddingcache/embeddingcache.py
embeddingcache/embeddingdb.py
embeddingcache/hashstringdb.py
embeddingcache-0.1.0.dist-info/LICENSE.txt
embeddingcache-0.1.0.dist-info/METADATA
embeddingcache-0.1.0.dist-info/WHEEL
embeddingcache-0.1.0.dist-info/top_level.txt
embeddingcache-0.1.0.dist-info/RECORD
