Metadata-Version: 2.1
Name: embeddingcache
Version: 0.1.0
Summary: Retrieve text embeddings, but cache them locally if we have already computed them.
Author-email: Joseph Turian <lastname@gmail.com>
License: Copyright 2023, Joseph Turian
Project-URL: Homepage, https://github.com/turian/embeddingcache
Project-URL: Bug Reports, https://github.com/turian/embeddingcache
Project-URL: Source, https://github.com/turian/embeddingcache
Keywords: sample,setuptools,development
Classifier: Development Status :: 3 - Alpha
Classifier: Intended Audience :: Developers
Classifier: Intended Audience :: Science/Research
Classifier: Topic :: Scientific/Engineering :: Artificial Intelligence
Classifier: License :: OSI Approved :: Apache Software License
Classifier: Programming Language :: Python :: 3
Classifier: Programming Language :: Python :: 3.7
Classifier: Programming Language :: Python :: 3.8
Classifier: Programming Language :: Python :: 3.9
Classifier: Programming Language :: Python :: 3.10
Classifier: Programming Language :: Python :: 3.11
Classifier: Programming Language :: Python :: 3 :: Only
Requires-Python: >=3.7
License-File: LICENSE.txt
Requires-Dist: SQLAlchemy
Requires-Dist: tqdm
Requires-Dist: python-slugify
Requires-Dist: sentence-transformers
Requires-Dist: numpy
Provides-Extra: dev
Requires-Dist: check-manifest ; extra == 'dev'
Provides-Extra: test
Requires-Dist: coverage ; extra == 'test'
